enapi/__init__.py
enapi/enapi.py
enapi-0.2.dist-info/LICENSE
enapi-0.2.dist-info/METADATA
enapi-0.2.dist-info/WHEEL
enapi-0.2.dist-info/top_level.txt
enapi-0.2.dist-info/RECORD
