Metadata-Version: 2.1
Name: enapi
Version: 0.2
Summary: Common API functionality
Home-page: https://github.com/kingmold/enapi
Author: Eric Nuno
Author-email: ericnuno@gmail.com
License: MIT
Platform: UNKNOWN
Classifier: Programming Language :: Python :: 3
Classifier: License :: OSI Approved :: MIT License
Classifier: Operating System :: OS Independent
